bcd_to_7seg.v
`timescale 1ns / 1ps

module bcd_to_7seg(
    input wire [15:0] bcd,
    input wire rst,
    input wire clk,
    output reg [6:0] seg,
    output reg [3:0] an
    );


    reg [3:0] current_digit;
    reg [1:0] digit;

    //Digit selection 125Hz refresh rate
    always @ (posedge clk, posedge rst) begin
        if (rst) digit <= 0; 
        else digit <= digit + 1;
    end

    //Segment multiplexing
    always @ (*) begin
        case (digit)
            2'd0: begin
                current_digit = bcd[15:12];
                an = 4'b1000;
            end
            2'd1: begin
                current_digit = bcd[11:8];
                an = 4'b0100;
            end
            2'd2: begin
                current_digit = bcd[7:4];
                an = 4'b0010;
            end
            2'd3: begin
                current_digit = bcd[3:0];
                an = 4'b0001;
            end
            default: begin
                current_digit = 4'b0000;
                an = 4'b0000;
            end
        endcase 

    end

    //Digit decoder
    always @ (*) begin
        case(current_digit)
            4'd0: seg = 7'b0000001;  // 0 
            4'd1: seg = 7'b1001111;  // 1 
            4'd2: seg = 7'b0010010;  // 2
            4'd3: seg = 7'b0000110;  // 3
            4'd4: seg = 7'b1001100;  // 4
            4'd5: seg = 7'b0100100;  // 5
            4'd6: seg = 7'b0100000;  // 6
            4'd7: seg = 7'b0001111;  // 7
            4'd8: seg = 7'b0000000;  // 8
            4'd9: seg = 7'b0000100;  // 9
            default: seg = 7'b1111111; //All off 
        endcase
    end 

endmodule

bcd_to_time.v
`timescale 1ns / 1ps

module bcd_to_time(
    input [11:0] count,
    output reg [15:0] time_out
    );

    reg [3:0] min_tens;
    reg [3:0] min_ones;
    reg [3:0] sec_tens;
    reg [3:0] sec_ones;
    
    always @ (*) begin
        min_tens = (count / 600);
        min_ones = (count / 60) % 10;
        
        sec_tens = (count % 60) / 10;
        sec_ones = (count % 60) % 10;

        time_out = {min_tens, min_ones, sec_tens, sec_ones};
    end
    
    
endmodule

sims/bcd_to_7seg_tb.v
`timescale 1ns / 1ps
`include "bcd_to_7seg.v"
`include "bcd_to_time.v"

module bcd_to_7seg_tb;

    // Inputs to bcd_to_time
    reg [11:0] count;
    
    // Outputs from bcd_to_time
    wire [15:0] time_out;
    
    // Inputs to bcd_to_7seg
    reg rst;
    reg clk;
    
    // Outputs from bcd_to_7seg
    wire [6:0] seg;
    wire [3:0] an;
    
    // Instantiate bcd_to_time
    bcd_to_time uut_time (
        .count(count),
        .time_out(time_out)
    );
    
    // Instantiate bcd_to_7seg
    bcd_to_7seg uut_seg (
        .bcd(time_out),
        .rst(rst),
        .clk(clk),
        .seg(seg),
        .an(an)
    );
    
    // Clock generation (8 ns period ~ 125 MHz, adjusted for 125 Hz refresh)
    initial begin
        clk = 0;
        forever #4 clk = ~clk;  // 125 MHz clock for simulation (scaled for visibility)
    end
    
    // Test procedure
    initial begin
        // Initialize inputs
        count = 0;
        rst = 1;
        
        // Reset pulse
        #10;
        rst = 0;
        
        // Test case 1: 00:00
        count = 12'd0;
        #100;  // Wait for several digit cycles
        $display("Test 1 - 00:00");
        display_output();
        
        // Test case 2: 01:30
        count = 12'd90;
        #100;
        $display("Test 2 - 01:30");
        display_output();
        
        // Test case 3: 05:45
        count = 12'd345;
        #100;
        $display("Test 3 - 05:45");
        display_output();
        
        // Test case 4: 59:59
        count = 12'd3599;
        #100;
        $display("Test 4 - 59:59");
        display_output();
        
        // Test case 5: 23:17
        count = 12'd1397;
        #100;
        $display("Test 5 - 23:17");
        display_output();
        
        // End simulation
        #50;
        $finish;
    end
    
    // Task to display current output
    task display_output;
        begin
            @(posedge clk);  // Sync to clock edge
            $display("Digit %d%d (an=%b): seg=%b", 
                     time_out[15:12], time_out[11:8], an, seg);
            @(posedge clk);
            $display("Digit %d%d (an=%b): seg=%b", 
                     time_out[11:8], time_out[7:4], an, seg);
            @(posedge clk);
            $display("Digit %d%d (an=%b): seg=%b", 
                     time_out[7:4], time_out[3:0], an, seg);
            @(posedge clk);
            $display("Digit %d%d (an=%b): seg=%b", 
                     time_out[3:0], time_out[15:12], an, seg);
            $display("-----");
        end
    endtask
    
    // Dump waveform for debugging
    initial begin
        $dumpfile("bcd_to_7seg_tb.vcd");
        $dumpvars(0, bcd_to_7seg_tb);
    end

endmodule

sims/bcd_to_7seg_tb.vcd
$date
	Tue Apr 01 18:48:18 2025
$end
$version
	Icarus Verilog
$end
$timescale
	1ps
$end
$scope module bcd_to_7seg_tb $end
$var wire 16 ! time_out [15:0] $end
$var wire 7 " seg [6:0] $end
$var wire 4 # an [3:0] $end
$var reg 1 $ clk $end
$var reg 12 % count [11:0] $end
$var reg 1 & rst $end
$scope module uut_seg $end
$var wire 1 $ clk $end
$var wire 1 & rst $end
$var wire 16 ' bcd [15:0] $end
$var reg 4 ( an [3:0] $end
$var reg 4 ) current_digit [3:0] $end
$var reg 2 * digit [1:0] $end
$var reg 7 + seg [6:0] $end
$upscope $end
$scope module uut_time $end
$var wire 12 , count [11:0] $end
$var reg 4 - min_ones [3:0] $end
$var reg 4 . min_tens [3:0] $end
$var reg 4 / sec_ones [3:0] $end
$var reg 4 0 sec_tens [3:0] $end
$var reg 16 1 time_out [15:0] $end
$upscope $end
$scope task display_output $end
$upscope $end
$upscope $end
$enddefinitions $end
$comment Show the parameter values. $end
$dumpall
$end
#0
$dumpvars
b0 1
b0 0
b0 /
b0 .
b0 -
b0 ,
b1 +
b0 *
b0 )
b1000 (
b0 '
1&
b0 %
0$
b1000 #
b1 "
b0 !
$end
#4000
1$
#8000
0$
#10000
0&
#12000
b100 #
b100 (
b1 *
1$
#16000
0$
#20000
b10 #
b10 (
b10 *
1$
#24000
0$
#28000
b1 #
b1 (
b11 *
1$
#32000
0$
#36000
b1000 #
b1000 (
b0 *
1$
#40000
0$
#44000
b100 #
b100 (
b1 *
1$
#48000
0$
#52000
b10 #
b10 (
b10 *
1$
#56000
0$
#60000
b1 #
b1 (
b11 *
1$
#64000
0$
#68000
b1000 #
b1000 (
b0 *
1$
#72000
0$
#76000
b100 #
b100 (
b1 *
1$
#80000
0$
#84000
b10 #
b10 (
b10 *
1$
#88000
0$
#92000
b1 #
b1 (
b11 *
1$
#96000
0$
#100000
b1000 #
b1000 (
b0 *
1$
#104000
0$
#108000
b100 #
b100 (
b1 *
1$
#112000
0$
#116000
b10 #
b10 (
b10 *
1$
#120000
0$
#124000
b1 #
b1 (
b11 *
1$
#128000
0$
#132000
b1000 #
b1000 (
b0 *
1$
#136000
0$
#140000
b1001111 "
b1001111 +
b100 #
b100 (
b1 )
b1 *
b100110000 !
b100110000 '
b100110000 1
b11 0
b1 -
b1011010 %
b1011010 ,
1$
#144000
0$
#148000
b110 "
b110 +
b10 #
b10 (
b11 )
b10 *
1$
#152000
0$
#156000
b1 "
b1 +
b1 #
b1 (
b0 )
b11 *
1$
#160000
0$
#164000
b1000 #
b1000 (
b0 *
1$
#168000
0$
#172000
b1001111 "
b1001111 +
b100 #
b100 (
b1 )
b1 *
1$
#176000
0$
#180000
b110 "
b110 +
b10 #
b10 (
b11 )
b10 *
1$
#184000
0$
#188000
b1 "
b1 +
b1 #
b1 (
b0 )
b11 *
1$
#192000
0$
#196000
b1000 #
b1000 (
b0 *
1$
#200000
0$
#204000
b1001111 "
b1001111 +
b100 #
b100 (
b1 )
b1 *
1$
#208000
0$
#212000
b110 "
b110 +
b10 #
b10 (
b11 )
b10 *
1$
#216000
0$
#220000
b1 "
b1 +
b1 #
b1 (
b0 )
b11 *
1$
#224000
0$
#228000
b1000 #
b1000 (
b0 *
1$
#232000
0$
#236000
b1001111 "
b1001111 +
b100 #
b100 (
b1 )
b1 *
1$
#240000
0$
#244000
b110 "
b110 +
b10 #
b10 (
b11 )
b10 *
1$
#248000
0$
#252000
b1 "
b1 +
b1 #
b1 (
b0 )
b11 *
1$
#256000
0$
#260000
b1000 #
b1000 (
b0 *
1$
#264000
0$
#268000
b100100 "
b100100 +
b100 #
b100 (
b101 )
b1 *
b10101000101 !
b10101000101 '
b10101000101 1
b101 /
b100 0
b101 -
b101011001 %
b101011001 ,
1$
#272000
0$
#276000
b1001100 "
b1001100 +
b10 #
b10 (
b100 )
b10 *
1$
#280000
0$
#284000
b100100 "
b100100 +
b1 #
b1 (
b101 )
b11 *
1$
#288000
0$
#292000
b1 "
b1 +
b1000 #
b1000 (
b0 )
b0 *
1$
#296000
0$
#300000
b100100 "
b100100 +
b100 #
b100 (
b101 )
b1 *
1$
#304000
0$
#308000
b1001100 "
b1001100 +
b10 #
b10 (
b100 )
b10 *
1$
#312000
0$
#316000
b100100 "
b100100 +
b1 #
b1 (
b101 )
b11 *
1$
#320000
0$
#324000
b1 "
b1 +
b1000 #
b1000 (
b0 )
b0 *
1$
#328000
0$
#332000
b100100 "
b100100 +
b100 #
b100 (
b101 )
b1 *
1$
#336000
0$
#340000
b1001100 "
b1001100 +
b10 #
b10 (
b100 )
b10 *
1$
#344000
0$
#348000
b100100 "
b100100 +
b1 #
b1 (
b101 )
b11 *
1$
#352000
0$
#356000
b1 "
b1 +
b1000 #
b1000 (
b0 )
b0 *
1$
#360000
0$
#364000
b100100 "
b100100 +
b100 #
b100 (
b101 )
b1 *
1$
#368000
0$
#372000
b1001100 "
b1001100 +
b10 #
b10 (
b100 )
b10 *
1$
#376000
0$
#380000
b100100 "
b100100 +
b1 #
b1 (
b101 )
b11 *
1$
#384000
0$
#388000
b1 "
b1 +
b1000 #
b1000 (
b0 )
b0 *
1$
#392000
0$
#396000
b100 #
b100 (
b1 *
b100 "
b100 +
b1001 )
b101100101011001 !
b101100101011001 '
b101100101011001 1
b1001 /
b101 0
b1001 -
b101 .
b111000001111 %
b111000001111 ,
1$
#400000
0$
#404000
b100100 "
b100100 +
b10 #
b10 (
b101 )
b10 *
1$
#408000
0$
#412000
b100 "
b100 +
b1 #
b1 (
b1001 )
b11 *
1$
#416000
0$
#420000
b100100 "
b100100 +
b1000 #
b1000 (
b101 )
b0 *
1$
#424000
0$
#428000
b100 "
b100 +
b100 #
b100 (
b1001 )
b1 *
1$
#432000
0$
#436000
b100100 "
b100100 +
b10 #
b10 (
b101 )
b10 *
1$
#440000
0$
#444000
b100 "
b100 +
b1 #
b1 (
b1001 )
b11 *
1$
#448000
0$
#452000
b100100 "
b100100 +
b1000 #
b1000 (
b101 )
b0 *
1$
#456000
0$
#460000
b100 "
b100 +
b100 #
b100 (
b1001 )
b1 *
1$
#464000
0$
#468000
b100100 "
b100100 +
b10 #
b10 (
b101 )
b10 *
1$
#472000
0$
#476000
b100 "
b100 +
b1 #
b1 (
b1001 )
b11 *
1$
#480000
0$
#484000
b100100 "
b100100 +
b1000 #
b1000 (
b101 )
b0 *
1$
#488000
0$
#492000
b100 "
b100 +
b100 #
b100 (
b1001 )
b1 *
1$
#496000
0$
#500000
b100100 "
b100100 +
b10 #
b10 (
b101 )
b10 *
1$
#504000
0$
#508000
b100 "
b100 +
b1 #
b1 (
b1001 )
b11 *
1$
#512000
0$
#516000
b100100 "
b100100 +
b1000 #
b1000 (
b101 )
b0 *
1$
#520000
0$
#524000
b100 #
b100 (
b1 *
b110 "
b110 +
b11 )
b10001100010111 !
b10001100010111 '
b10001100010111 1
b111 /
b1 0
b11 -
b10 .
b10101110101 %
b10101110101 ,
1$
#528000
0$
#532000
b1001111 "
b1001111 +
b10 #
b10 (
b1 )
b10 *
1$
#536000
0$
#540000
b1111 "
b1111 +
b1 #
b1 (
b111 )
b11 *
1$
#544000
0$
#548000
b10010 "
b10010 +
b1000 #
b1000 (
b10 )
b0 *
1$
#552000
0$
#556000
b110 "
b110 +
b100 #
b100 (
b11 )
b1 *
1$
#560000
0$
#564000
b1001111 "
b1001111 +
b10 #
b10 (
b1 )
b10 *
1$
#568000
0$
#572000
b1111 "
b1111 +
b1 #
b1 (
b111 )
b11 *
1$
#576000
0$
#580000
b10010 "
b10010 +
b1000 #
b1000 (
b10 )
b0 *
1$
#584000
0$
#588000
b110 "
b110 +
b100 #
b100 (
b11 )
b1 *
1$
#592000
0$
#596000
b1001111 "
b1001111 +
b10 #
b10 (
b1 )
b10 *
1$
#600000
0$
#604000
b1111 "
b1111 +
b1 #
b1 (
b111 )
b11 *
1$
#608000
0$
#612000
b10010 "
b10010 +
b1000 #
b1000 (
b10 )
b0 *
1$
#616000
0$
#620000
b110 "
b110 +
b100 #
b100 (
b11 )
b1 *
1$
#624000
0$
#628000
b1001111 "
b1001111 +
b10 #
b10 (
b1 )
b10 *
1$
#632000
0$
#636000
b1111 "
b1111 +
b1 #
b1 (
b111 )
b11 *
1$
#640000
0$
#644000
b10010 "
b10010 +
b1000 #
b1000 (
b10 )
b0 *
1$
#648000
0$
#652000
b110 "
b110 +
b100 #
b100 (
b11 )
b1 *
1$
#656000
0$
#660000
b1001111 "
b1001111 +
b10 #
b10 (
b1 )
b10 *
1$
#664000
0$
#668000
b1111 "
b1111 +
b1 #
b1 (
b111 )
b11 *
1$
#672000
0$
#676000
b10010 "
b10010 +
b1000 #
b1000 (
b10 )
b0 *
1$
#680000
0$
#684000
b110 "
b110 +
b100 #
b100 (
b11 )
b1 *
1$
#688000
0$
#692000
b1001111 "
b1001111 +
b10 #
b10 (
b1 )
b10 *
1$
#696000
0$
#700000
b1111 "
b1111 +
b1 #
b1 (
b111 )
b11 *
1$
